BWFM/__init__.py
BWFM/util.py
BWFM/Ui/about.py
BWFM/Ui/about.ui
BWFM/Ui/mainwindow.py
BWFM/Ui/mainwindow.ui
BWFM/Ui/settings.py
BWFM/Ui/settings.ui
BWFM/Ui/ui_py.sh
BWFM-1.1.2.dist-info/LICENSE
BWFM-1.1.2.dist-info/METADATA
BWFM-1.1.2.dist-info/WHEEL
BWFM-1.1.2.dist-info/entry_points.txt
BWFM-1.1.2.dist-info/top_level.txt
BWFM-1.1.2.dist-info/RECORD
